textile2rst-0.0.3.dist-info/metadata.json
textile2rst-0.0.3.dist-info/METADATA
textile2rst-0.0.3.dist-info/WHEEL
textile2rst-0.0.3.dist-info/RECORD
textile2rst-0.0.3.dist-info/top_level.txt
textile2rst-0.0.3.dist-info/DESCRIPTION.rst
textile2rst/textile2rst.py
textile2rst/__init__.py
textile2rst/__main__.py
